imgur2pdf/__init__.py
imgur2pdf/imgur2pdf.py
upload2remarkable/__init__.py
upload2remarkable/upload2remarkable.py
upload2remarkable/uploader.py
imgur2pdf-0.2.0.dist-info/entry_points.txt
imgur2pdf-0.2.0.dist-info/WHEEL
imgur2pdf-0.2.0.dist-info/METADATA
imgur2pdf-0.2.0.dist-info/RECORD
