Metadata-Version: 2.1
Name: imgur2pdf
Version: 0.2.0
Summary: 
Author: mrfyda
Author-email: mrfyda@gmail.com
Requires-Python: >=3.8,<4.0
Classifier: Programming Language :: Python :: 3
Classifier: Programming Language :: Python :: 3.8
Classifier: Programming Language :: Python :: 3.9
Requires-Dist: Pillow (>=8.0.1,<9.0.0)
Requires-Dist: click (>=7.1.2,<8.0.0)
Requires-Dist: imgurpython (>=1.1.7,<2.0.0)
Requires-Dist: requests (>=2.24.0,<3.0.0)
Requires-Dist: rmapy (>=0.2.3,<0.3.0)
